asgi_middleware_static_file/__init__.py
asgi_middleware_static_file/core.py
asgimiddlewarestaticfile-0.6.2.dist-info/licenses/LICENSE
asgimiddlewarestaticfile-0.6.2.dist-info/METADATA
asgimiddlewarestaticfile-0.6.2.dist-info/WHEEL
asgimiddlewarestaticfile-0.6.2.dist-info/top_level.txt
asgimiddlewarestaticfile-0.6.2.dist-info/RECORD
