Metadata-Version: 2.4
Name: ASGIMiddlewareStaticFile
Version: 0.6.2
Summary: ASGI Middleware for serving Static File.
Author: Rex Zhang
Author-email: rex.zhang@gmail.com
Project-URL: homepage, https://github.com/rexzhang/asgi-middleware-static-file
Project-URL: documentation, https://github.com/rexzhang/asgi-middleware-static-file/blob/main/README.md
Project-URL: repository, https://github.com/rexzhang/asgi-middleware-static-file
Project-URL: changelog, https://github.com/rexzhang/asgi-middleware-static-file/blob/main/README.md#history
Keywords: staticfile,middleware,asgi,asyncio
Classifier: Development Status :: 4 - Beta
Classifier: Programming Language :: Python :: 3.7
Classifier: Programming Language :: Python :: 3.8
Classifier: Programming Language :: Python :: 3.9
Classifier: Programming Language :: Python :: 3.10
Classifier: Programming Language :: Python :: 3.11
Classifier: Programming Language :: Python :: 3.12
Classifier: Programming Language :: Python :: 3.13
Classifier: Programming Language :: Python :: 3.14
Classifier: Topic :: Software Development :: Libraries :: Python Modules
Requires-Python: >=3.7
License-File: LICENSE
Requires-Dist: aiofiles>=23.2.1
Dynamic: license-file
